py_metarium/__init__.py
py_metarium/metarium.py
py_metarium/chains/__init__.py
py_metarium/chains/base.py
py_metarium/chains/substrate.py
py_metarium/utils/__init__.py
py_metarium/utils/constants.py
py_metarium/utils/exceptions.py
py_metarium/utils/helpers.py
py_metarium-0.0.2.51.dist-info/LICENSE
py_metarium-0.0.2.51.dist-info/METADATA
py_metarium-0.0.2.51.dist-info/WHEEL
py_metarium-0.0.2.51.dist-info/top_level.txt
py_metarium-0.0.2.51.dist-info/RECORD
