Metadata-Version: 2.1
Name: py-metarium
Version: 0.0.2.51
Summary: Python package for Metarium
Author: MetariumProject
Project-URL: Homepage, https://github.com/MetariumProject/py-metarium
Project-URL: Bug Tracker, https://github.com/MetariumProject/py-metarium/issues
Classifier: Programming Language :: Python :: 3
Classifier: License :: OSI Approved :: MIT License
Classifier: Operating System :: OS Independent
Requires-Python: >=3.9
License-File: LICENSE
Requires-Dist: substrate-interface (==1.4.0)
